photonai_graph/GraphConversions.py
photonai_graph/GraphMeasures.json
photonai_graph/GraphUtilities.py
photonai_graph/IgraphMeasures.json
photonai_graph/PopulationAveragingTransform.py
photonai_graph/__init__.py
photonai_graph/photonai_graph.json
photonai_graph/util.py
photonai_graph/version.py
photonai_graph/Controllability/__init__.py
photonai_graph/Controllability/controllability_functions.py
photonai_graph/Controllability/controllability_measures.py
photonai_graph/DynamicUtils/__init__.py
photonai_graph/DynamicUtils/cofluct_functions.py
photonai_graph/DynamicUtils/cofluct_transform.py
photonai_graph/GraphConstruction/__init__.py
photonai_graph/GraphConstruction/graph_constructor.py
photonai_graph/GraphConstruction/graph_constructor_knn.py
photonai_graph/GraphConstruction/graph_constructor_percentage.py
photonai_graph/GraphConstruction/graph_constructor_percentage_window.py
photonai_graph/GraphConstruction/graph_constructor_random_walks.py
photonai_graph/GraphConstruction/graph_constructor_spatial.py
photonai_graph/GraphConstruction/graph_constructor_threshold.py
photonai_graph/GraphConstruction/graph_constructor_threshold_window.py
photonai_graph/GraphConstruction/ho_coords.csv
photonai_graph/GraphEmbedding/__init__.py
photonai_graph/GraphEmbedding/graph_embedding_base.py
photonai_graph/GraphEmbedding/graph_embedding_hope.py
photonai_graph/GraphEmbedding/graph_embedding_laplacian_eigenmaps.py
photonai_graph/GraphEmbedding/graph_embedding_locally_linear_embedding.py
photonai_graph/GraphKernels/GrakelTransformer.py
photonai_graph/GraphKernels/__init__.py
photonai_graph/GraphKernels/grakel_adapter.py
photonai_graph/Measures/AbstractMeasureTransform.py
photonai_graph/Measures/IgraphMeasureTransform.py
photonai_graph/Measures/MeasureAdapter.py
photonai_graph/Measures/NetworkxMeasureTransform.py
photonai_graph/Measures/__init__.py
photonai_graph/NeuralNets/GATModel.py
photonai_graph/NeuralNets/GCNModel.py
photonai_graph/NeuralNets/NNUtilities.py
photonai_graph-0.2.5.dist-info/AUTHORS
photonai_graph-0.2.5.dist-info/LICENSE
photonai_graph-0.2.5.dist-info/METADATA
photonai_graph-0.2.5.dist-info/WHEEL
photonai_graph-0.2.5.dist-info/pbr.json
photonai_graph-0.2.5.dist-info/top_level.txt
photonai_graph-0.2.5.dist-info/RECORD
