Metadata-Version: 2.1
Name: photonai-graph
Version: 0.2.5
Summary: PHOTON Graph - Graph machine learning with photonai.
Home-page: https://www.photon-ai.com/
Author: PHOTON Team
Author-email: hahnt@uni-muenster.de
License: MIT
Download-URL: https://pypi.org/project/photonai_graph/#files
Project-URL: Source Code, https://github.com/wwu-mmll/photonai_graph
Project-URL: Documentation, https://wwu-mmll.github.io/photonai_graph/
Project-URL: Bug Tracker, https://github.com/wwu-mmll/photonai_graph/issues
Keywords: machine learning,deep learning,graph convolutional neural networks,graphs
Platform: UNKNOWN
Classifier: License :: OSI Approved :: MIT License
Classifier: Topic :: Software Development :: Libraries :: Python Modules
Classifier: Topic :: Scientific/Engineering :: Artificial Intelligence
Classifier: Intended Audience :: Science/Research
License-File: LICENSE
License-File: AUTHORS
Requires-Dist: photonai
Requires-Dist: networkx (<3.1)
Requires-Dist: pydot
Requires-Dist: dgl (==1.0.0)
Requires-Dist: nxt-gem
Requires-Dist: grakel
Requires-Dist: pandas
Requires-Dist: numpy (<=1.24.2)
Requires-Dist: scipy
Requires-Dist: tensorflow
Requires-Dist: torch
Requires-Dist: tqdm
Requires-Dist: pbr
Requires-Dist: igraph
